pypdbot/__init__.py
pypdbot/pumpdumppyqtlite.py
pypdbot/pypdbot.py
pypdbot-1.0.4.dist-info/METADATA
pypdbot-1.0.4.dist-info/WHEEL
pypdbot-1.0.4.dist-info/entry_points.txt
pypdbot-1.0.4.dist-info/license.txt
pypdbot-1.0.4.dist-info/top_level.txt
pypdbot-1.0.4.dist-info/RECORD
